guardian_mental_health-0.2.4.dist-info/licenses/LICENSE
mental_monitoring/__init__.py
mental_monitoring/config.py
mental_monitoring/main.py
mental_monitoring/config/__init__.py
mental_monitoring/config/config.py
mental_monitoring/config/optimization_config.py
mental_monitoring/dashboard/__init__.py
mental_monitoring/dashboard/streamlit_app.py
mental_monitoring/data/__init__.py
mental_monitoring/data/samples.json
mental_monitoring/discord_bot/__init__.py
mental_monitoring/discord_bot/monitor.py
mental_monitoring/models/__init__.py
mental_monitoring/models/training.py
mental_monitoring/models/transformer_classifier.py
mental_monitoring/utils/__init__.py
mental_monitoring/utils/model_downloader.py
mental_monitoring/utils/optimized_inference.py
mental_monitoring/utils/tokenizer.py
guardian_mental_health-0.2.4.dist-info/METADATA
guardian_mental_health-0.2.4.dist-info/WHEEL
guardian_mental_health-0.2.4.dist-info/entry_points.txt
guardian_mental_health-0.2.4.dist-info/top_level.txt
guardian_mental_health-0.2.4.dist-info/RECORD
