Metadata-Version: 2.4
Name: guardian-mental-health
Version: 0.2.4
Summary: Mental health monitoring system using transformer models with RTX optimization
Home-page: https://github.com/scoorpion1008/Guardian
Author: Carlos Hernandez
Author-email: Carlos Hernandez <scorpioon1008@ai-withcarlos.com>
License-Expression: MIT
Project-URL: Bug Tracker, https://github.com/scoorpion1008/Guardian/issues
Project-URL: Documentation, https://github.com/scoorpion1008/Guardian/wiki
Project-URL: Source Code, https://github.com/scoorpion1008/Guardian
Project-URL: PyPI, https://pypi.org/project/guardian-mental-health/
Keywords: mental health,nlp,transformers,pytorch,discord,machine learning,bert,rtx,onnx
Classifier: Programming Language :: Python :: 3
Classifier: Programming Language :: Python :: 3.8
Classifier: Programming Language :: Python :: 3.9
Classifier: Programming Language :: Python :: 3.10
Classifier: Programming Language :: Python :: 3.11
Classifier: Operating System :: OS Independent
Classifier: Topic :: Scientific/Engineering :: Artificial Intelligence
Classifier: Topic :: Communications :: Chat
Classifier: Topic :: Text Processing :: Linguistic
Classifier: Development Status :: 4 - Beta
Classifier: Intended Audience :: Science/Research
Classifier: Intended Audience :: Education
Requires-Python: >=3.8
License-File: LICENSE
Requires-Dist: torch>=2.0.0
Requires-Dist: torchvision>=0.15.0
Requires-Dist: torchaudio>=2.0.0
Requires-Dist: transformers>=4.30.0
Requires-Dist: pandas>=2.0.0
Requires-Dist: numpy>=1.24.0
Requires-Dist: scikit-learn>=1.3.0
Requires-Dist: streamlit>=1.25.0
Requires-Dist: plotly>=5.15.0
Requires-Dist: matplotlib>=3.7.0
Requires-Dist: discord.py>=2.3.0
Requires-Dist: tqdm>=4.65.0
Requires-Dist: requests>=2.30.0
Requires-Dist: python-dotenv>=1.0.0
Requires-Dist: ninja
Requires-Dist: accelerate>=0.20.0
Provides-Extra: dev
Requires-Dist: pytest>=7.0.0; extra == "dev"
Requires-Dist: pytest-cov>=4.0.0; extra == "dev"
Requires-Dist: black>=23.0.0; extra == "dev"
Requires-Dist: isort>=5.12.0; extra == "dev"
Requires-Dist: pylint>=2.17.0; extra == "dev"
Requires-Dist: mypy>=1.4.0; extra == "dev"
Requires-Dist: twine>=4.0.0; extra == "dev"
Requires-Dist: build>=1.0.0; extra == "dev"
Requires-Dist: wheel>=0.42.0; extra == "dev"
Provides-Extra: optimize
Requires-Dist: onnx>=1.14.0; extra == "optimize"
Requires-Dist: onnxruntime-gpu>=1.16.0; platform_system != "Darwin" and extra == "optimize"
Requires-Dist: onnxruntime>=1.16.0; platform_system == "Darwin" and extra == "optimize"
Provides-Extra: rtx
Requires-Dist: onnx>=1.14.0; extra == "rtx"
Requires-Dist: onnxruntime-gpu>=1.16.0; extra == "rtx"
Requires-Dist: ninja>=1.10.0; extra == "rtx"
Requires-Dist: accelerate>=0.20.0; extra == "rtx"
Provides-Extra: deploy
Requires-Dist: gunicorn>=21.0.0; extra == "deploy"
Requires-Dist: uvicorn>=0.23.0; extra == "deploy"
Requires-Dist: fastapi>=0.100.0; extra == "deploy"
Provides-Extra: all
Requires-Dist: onnx>=1.14.0; extra == "all"
Requires-Dist: onnxruntime-gpu>=1.16.0; platform_system != "Darwin" and extra == "all"
Requires-Dist: onnxruntime>=1.16.0; platform_system == "Darwin" and extra == "all"
Requires-Dist: ninja>=1.10.0; extra == "all"
Requires-Dist: accelerate>=0.20.0; extra == "all"
Requires-Dist: gunicorn>=21.0.0; extra == "all"
Requires-Dist: uvicorn>=0.23.0; extra == "all"
Requires-Dist: fastapi>=0.100.0; extra == "all"
Dynamic: author
Dynamic: description
Dynamic: description-content-type
Dynamic: home-page
Dynamic: license-file
Dynamic: project-url
Dynamic: provides-extra
Dynamic: requires-dist
Dynamic: requires-python
